tesseract_robotics/__init__.py
tesseract_robotics/data/__init__.py
tesseract_robotics/data/task_composer_config/task_composer_plugins.yaml
tesseract_robotics/data/task_composer_config/task_composer_plugins.yaml.schema
tesseract_robotics/data/task_composer_config/task_composer_plugins_no_trajopt_ifopt.yaml
tesseract_robotics/data/tesseract_support/meshes/abb_irb2400/irb2400/collision/base_link.stl
tesseract_robotics/data/tesseract_support/meshes/abb_irb2400/irb2400/collision/link_1.stl
tesseract_robotics/data/tesseract_support/meshes/abb_irb2400/irb2400/collision/link_2.stl
tesseract_robotics/data/tesseract_support/meshes/abb_irb2400/irb2400/collision/link_2_whole.stl
tesseract_robotics/data/tesseract_support/meshes/abb_irb2400/irb2400/collision/link_3.stl
tesseract_robotics/data/tesseract_support/meshes/abb_irb2400/irb2400/collision/link_4.stl
tesseract_robotics/data/tesseract_support/meshes/abb_irb2400/irb2400/collision/link_5.stl
tesseract_robotics/data/tesseract_support/meshes/abb_irb2400/irb2400/collision/link_6.stl
tesseract_robotics/data/tesseract_support/meshes/abb_irb2400/irb2400/visual/base_link.dae
tesseract_robotics/data/tesseract_support/meshes/abb_irb2400/irb2400/visual/link_1.dae
tesseract_robotics/data/tesseract_support/meshes/abb_irb2400/irb2400/visual/link_2.dae
tesseract_robotics/data/tesseract_support/meshes/abb_irb2400/irb2400/visual/link_3.dae
tesseract_robotics/data/tesseract_support/meshes/abb_irb2400/irb2400/visual/link_4.dae
tesseract_robotics/data/tesseract_support/meshes/abb_irb2400/irb2400/visual/link_5.dae
tesseract_robotics/data/tesseract_support/meshes/abb_irb2400/irb2400/visual/link_6.dae
tesseract_robotics/data/tesseract_support/meshes/abb_irb2400/irb2400_common/collision/base_link.stl
tesseract_robotics/data/tesseract_support/meshes/abb_irb2400/irb2400_common/collision/link_1.stl
tesseract_robotics/data/tesseract_support/meshes/abb_irb2400/irb2400_common/collision/link_2.stl
tesseract_robotics_nanobind-0.7.3.dist-info/METADATA
tesseract_robotics_nanobind-0.7.3.dist-info/WHEEL
tesseract_robotics_nanobind-0.7.3.dist-info/entry_points.txt
tesseract_robotics_nanobind-0.7.3.dist-info/RECORD
