Metadata-Version: 2.1
Name: tesseract-robotics-nanobind
Version: 0.7.3
Summary: Tesseract robotics Python bindings (nanobind)
Author-Email: Jelle Feringa <jelle@terrestrial.construction>, John Wason <wason@wasontech.com>
Classifier: Development Status :: 4 - Beta
Classifier: Topic :: Scientific/Engineering
Classifier: Operating System :: Unix
Classifier: Operating System :: POSIX
Classifier: Programming Language :: Python
Classifier: Programming Language :: Python :: 3.9
Classifier: Programming Language :: Python :: 3.10
Classifier: Programming Language :: Python :: 3.11
Classifier: Programming Language :: Python :: 3.12
Classifier: Programming Language :: C++
Classifier: Programming Language :: Python :: Implementation :: CPython
Classifier: License :: OSI Approved :: Apache Software License
Project-URL: Homepage, https://github.com/tesseract-robotics/tesseract_nanobind
Project-URL: Repository, https://github.com/tesseract-robotics/tesseract_nanobind
Requires-Python: >=3.9
Requires-Dist: numpy>=1.21.0
Requires-Dist: loguru>=0.7.0
